Metadata-Version: 2.1
Name: localvolts-api
Version: 0.9.3
Summary: A Python wrapper for the LocalVolts API
Home-page: https://github.com/powston/localvolts
Author: Ian Connor
Author-email: ian@powston.com
License: UNKNOWN
Platform: UNKNOWN
Classifier: Programming Language :: Python :: 3
Classifier: License :: OSI Approved :: MIT License
Classifier: Operating System :: OS Independent
Requires-Python: >=3.7
License-File: LICENSE
Requires-Dist: requests
Requires-Dist: pandas
